investimentos/__init__.py
investimentos/investimentos.py
meu_investimento_alura_djflucena-0.1.1.dist-info/METADATA
meu_investimento_alura_djflucena-0.1.1.dist-info/WHEEL
meu_investimento_alura_djflucena-0.1.1.dist-info/top_level.txt
meu_investimento_alura_djflucena-0.1.1.dist-info/RECORD
