Metadata-Version: 2.4
Name: meu_investimento_alura_djflucena
Version: 0.1.1
Summary: Uma biblioteca para cálculos de investimentos.
Home-page: https://github.com/djflucena/meu_investimento
Author: David J F de Lucena
Author-email: djflucena@sefaz.al.gov.br
Classifier: Programming Language :: Python :: 3
Classifier: License :: OSI Approved :: MIT License
Classifier: Operating System :: OS Independent
Requires-Python: >=3.6
Dynamic: author
Dynamic: author-email
Dynamic: classifier
Dynamic: home-page
Dynamic: requires-python
Dynamic: summary
